django_major_event_log-0.1.2.dist-info/METADATA
django_major_event_log-0.1.2.dist-info/RECORD
django_major_event_log-0.1.2.dist-info/WHEEL
django_major_event_log-0.1.2.dist-info/top_level.txt
major_event_log/__init__.py
major_event_log/admin.py
major_event_log/feeds.py
major_event_log/models.py
major_event_log/urls.py
major_event_log/views.py
major_event_log/migrations/0001_initial.py
major_event_log/migrations/0002_auto_20180911_1613.py
major_event_log/migrations/__init__.py
major_event_log/templates/major-event-log/about.html
major_event_log/templates/major-event-log/base.html
major_event_log/templates/major-event-log/button_grp_bottom.html
major_event_log/templates/major-event-log/event_atom.xml
major_event_log/templates/major-event-log/event_details.html
major_event_log/templates/major-event-log/event_premis.xml
major_event_log/templates/major-event-log/index.html
major_event_log/templates/major-event-log/navbar.html
major_event_log/templates/major-event-log/pagination.html
